<NetworkInterface version="2.0">
<id>1</id>
<IPAddress version="2.0">
<ipVersion>dual</ipVersion>
<addressingType>static</addressingType>
<ipAddress>192.217.72.31</ipAddress>
<subnetMask>255.255.255.0</subnetMask>
<ipv6Address>::</ipv6Address>
<bitMask>0</bitMask>
<DefaultGateway>
<ipAddress>192.217.72.1</ipAddress>
<ipv6Address>::</ipv6Address>
</DefaultGateway>
<PrimaryDNS>
<ipAddress>8.8.8.8</ipAddress>
</PrimaryDNS>
<SecondaryDNS>
<ipAddress>8.8.4.4</ipAddress>
</SecondaryDNS>
<Ipv6Mode>
<ipV6AddressingType>ra</ipV6AddressingType>
<ipv6AddressList>
<v6Address>
<id>1</id>
<type>manual</type>
<address>::</address>
<bitMask>0</bitMask>
</v6Address>
</ipv6AddressList>
</Ipv6Mode>
</IPAddress>
<Discovery version="2.0">
<UPnP>
<enabled>false</enabled>
</UPnP>
<Zeroconf>
<enabled>true</enabled>
</Zeroconf>
</Discovery>
<Link version="2.0">
<MACAddress>00:00:00:00:00:00</MACAddress>
<autoNegotiation>true</autoNegotiation>
<speed>10</speed>
<duplex>half</duplex>
<MTU>1500</MTU>
</Link>
</NetworkInterface>